CHANGES.rst
CONTRIBUTORS.rst
MANIFEST.in
README.rst
setup.cfg
setup.py
docs/LICENSE.GPL
docs/LICENSE.rst
docs/README
docs/readthedocs-requirements.txt
docs/_images/README
docs/_images/settings-colophon_text.png
docs/_images/settings-color_option.png
docs/_images/settings-debug.png
docs/_images/settings-email.png
docs/_images/settings-footer_option.png
docs/_images/settings-footer_text.png
docs/_images/settings-header_option.png
docs/_images/settings-hide_colophon.png
docs/_images/settings-hide_footer.png
docs/_images/settings-hide_searchbox.png
docs/_images/settings-layout_option.png
docs/_images/settings-pattern_option.png
docs/_images/settings-phone_number.png
docs/_images/settings-site_favicon.png
docs/_images/settings-slogan.png
docs/_images/settings.png
docs/_images/setup_select_add_on.png
docs/_images/setup_select_add_on_installable.png
docs/source/conf.py
docs/source/configuration.rst
docs/source/diazo.rst
docs/source/index.rst
docs/source/theming.rst
docs/source/_static/.gitkeep
docs/source/_static/logo.png
docs/source/_templates/.gitkeep
src/spirit/__init__.py
src/spirit.plone.theming.egg-info/PKG-INFO
src/spirit.plone.theming.egg-info/SOURCES.txt
src/spirit.plone.theming.egg-info/dependency_links.txt
src/spirit.plone.theming.egg-info/entry_points.txt
src/spirit.plone.theming.egg-info/namespace_packages.txt
src/spirit.plone.theming.egg-info/not-zip-safe
src/spirit.plone.theming.egg-info/requires.txt
src/spirit.plone.theming.egg-info/top_level.txt
src/spirit/plone/__init__.py
src/spirit/plone/theming/__init__.py
src/spirit/plone/theming/config.py
src/spirit/plone/theming/configure.zcml
src/spirit/plone/theming/interfaces.py
src/spirit/plone/theming/profiles.zcml
src/spirit/plone/theming/setuphandlers.py
src/spirit/plone/theming/testing.py
src/spirit/plone/theming/utils.py
src/spirit/plone/theming/vocabularies.py
src/spirit/plone/theming/vocabularies.zcml
src/spirit/plone/theming/browser/__init__.py
src/spirit/plone/theming/browser/configure.zcml
src/spirit/plone/theming/browser/controlpanel.py
src/spirit/plone/theming/browser/favicon.py
src/spirit/plone/theming/browser/logo.py
src/spirit/plone/theming/browser/viewlets.py
src/spirit/plone/theming/browser/static/.gitkeep
src/spirit/plone/theming/browser/templates/diazo_snippets.pt
src/spirit/plone/theming/browser/templates/logo.pt
src/spirit/plone/theming/locales/manual.pot
