Metadata-Version: 1.1
Name: spirit.plone.theming
Version: 0.8
Summary: Theming extensions for Plone Websites.
Home-page: https://github.com/it-spirit/spirit.plone.theming
Author: it-spirit
Author-email: thomas.massmann@it-spir.it
License: GPL version 2
Download-URL: http://pypi.python.org/pypi/spirit.plone.theming
Keywords: plone zope theming
Platform: UNKNOWN
Classifier: Development Status :: 5 - Production/Stable
Classifier: Environment :: Web Environment
Classifier: Framework :: Plone
Classifier: Framework :: Plone :: 4.2
Classifier: Framework :: Plone :: 4.3
Classifier: Framework :: Plone :: 5.0
Classifier: Framework :: Plone :: 5.1
Classifier: Intended Audience :: Developers
Classifier: License :: OSI Approved :: GNU General Public License v2 (GPLv2)
Classifier: Programming Language :: Python
Classifier: Programming Language :: Python :: 2.7
